Workbook

Sheet Dashboard
B1: 🏦 MR SHAHZEB HUSSAIN — CAPITEC STATEMENT TRACKER
B2: 01 April 2026 → 13 May 2026 | Account: 2281843307
B4: ACCOUNT OVERVIEW
B5: 💰 Opening Balance | D5: 📉 Closing Balance | F5: ✅ Available Balance
B6: R2 055.25 | D6: R1 932.72 | F6: R1 770.72
B9: MONEY IN vs MONEY OUT
B10: Money In | E10: Money Out (excl. fees)
B11: =IFERROR(SUMIF(Transactions!C:C,"Income",Transactions!D:D)+SUMIF(Transactions!C:C,"Deposit",Transactions!D:D)+SUMIF(Transactions!C:C,"Interest",Transactions!D:D)+SUMIF(Transactions!C:C,"Transfer",Transactions!D:D),0) -> 5500.13 | E11: =IFERROR(SUMIF(Transactions!C:C,"Card",Transactions!G:G)+SUMIF(Transactions!C:C,"EFT",Transactions!G:G)+SUMIF(Transactions!C:C,"Online",Transactions!G:G)+SUMIF(Transactions!C:C,"Prepaid",Transactions!G:G),0) -> 5431.38
B13: SPENDING ANALYSIS BY CATEGORY (XLOOKUP — live from Transactions)
B14: Category | C14: Spent (R) | D14: Limit (R) | E14: Remaining (R) | F14: % Used | G14: Status
B15: Takeaways | C15: =IFERROR(SUMIF(Transactions!E:E,B15,Transactions!G:G),0) -> 1015.5 | D15: =IFERROR(xlookup(B15,Categories!$A$2:$A$20,Categories!$B$2:$B$20,0),0) -> 0 | E15: =IFERROR(D15-C15,0) -> -1015.5 | F15: =IFERROR(C15/D15,0) -> 0 | G15: =IFERROR(IF(D15=0,"N/A",IF(C15>D15,"🔴 Over Budget",IF(C15/D15>0.8,"🟡 Near Limit","✅ On Track"))),"N/A") -> N/A
B16: Groceries | C16: =IFERROR(SUMIF(Transactions!E:E,B16,Transactions!G:G),0) -> 113.5 | D16: =IFERROR(xlookup(B16,Categories!$A$2:$A$20,Categories!$B$2:$B$20,0),0) -> 0 | E16: =IFERROR(D16-C16,0) -> -113.5 | F16: =IFERROR(C16/D16,0) -> 0 | G16: =IFERROR(IF(D16=0,"N/A",IF(C16>D16,"🔴 Over Budget",IF(C16/D16>0.8,"🟡 Near Limit","✅ On Track"))),"N/A") -> N/A
B17: Public Transport | C17: =IFERROR(SUMIF(Transactions!E:E,B17,Transactions!G:G),0) -> 382 | D17: =IFERROR(xlookup(B17,Categories!$A$2:$A$20,Categories!$B$2:$B$20,0),0) -> 0 | E17: =IFERROR(D17-C17,0) -> -382 | F17: =IFERROR(C17/D17,0) -> 0 | G17: =IFERROR(IF(D17=0,"N/A",IF(C17>D17,"🔴 Over Budget",IF(C17/D17>0.8,"🟡 Near Limit","✅ On Track"))),"N/A") -> N/A
B18: Cellphone | C18: =IFERROR(SUMIF(Transactions!E:E,B18,Transactions!G:G),0) -> 660 | D18: =IFERROR(xlookup(B18,Categories!$A$2:$A$20,Categories!$B$2:$B$20,0),0) -> 0 | E18: =IFERROR(D18-C18,0) -> -660 | F18: =IFERROR(C18/D18,0) -> 0 | G18: =IFERROR(IF(D18=0,"N/A",IF(C18>D18,"🔴 Over Budget",IF(C18/D18>0.8,"🟡 Near Limit","✅ On Track"))),"N/A") -> N/A
B19: Movies | C19: =IFERROR(SUMIF(Transactions!E:E,B19,Transactions!G:G),0) -> 299.9 | D19: =IFERROR(xlookup(B19,Categories!$A$2:$A$20,Categories!$B$2:$B$20,0),0) -> 0 | E19: =IFERROR(D19-C19,0) -> -299.9 | F19: =IFERROR(C19/D19,0) -> 0 | G19: =IFERROR(IF(D19=0,"N/A",IF(C19>D19,"🔴 Over Budget",IF(C19/D19>0.8,"🟡 Near Limit","✅ On Track"))),"N/A") -> N/A
B20: Restaurants | C20: =IFERROR(SUMIF(Transactions!E:E,B20,Transactions!G:G),0) -> 199 | D20: =IFERROR(xlookup(B20,Categories!$A$2:$A$20,Categories!$B$2:$B$20,0),0) -> 0 | E20: =IFERROR(D20-C20,0) -> -199 | F20: =IFERROR(C20/D20,0) -> 0 | G20: =IFERROR(IF(D20=0,"N/A",IF(C20>D20,"🔴 Over Budget",IF(C20/D20>0.8,"🟡 Near Limit","✅ On Track"))),"N/A") -> N/A
B21: Online Store | C21: =IFERROR(SUMIF(Transactions!E:E,B21,Transactions!G:G),0) -> 130.99 | D21: =IFERROR(xlookup(B21,Categories!$A$2:$A$20,Categories!$B$2:$B$20,0),0) -> 0 | E21: =IFERROR(D21-C21,0) -> -130.99 | F21: =IFERROR(C21/D21,0) -> 0 | G21: =IFERROR(IF(D21=0,"N/A",IF(C21>D21,"🔴 Over Budget",IF(C21/D21>0.8,"🟡 Near Limit","✅ On Track"))),"N/A") -> N/A
B22: Digital Payments | C22: =IFERROR(SUMIF(Transactions!E:E,B22,Transactions!G:G),0) -> 175 | D22: =IFERROR(xlookup(B22,Categories!$A$2:$A$20,Categories!$B$2:$B$20,0),0) -> 0 | E22: =IFERROR(D22-C22,0) -> -175 | F22: =IFERROR(C22/D22,0) -> 0 | G22: =IFERROR(IF(D22=0,"N/A",IF(C22>D22,"🔴 Over Budget",IF(C22/D22>0.8,"🟡 Near Limit","✅ On Track"))),"N/A") -> N/A
B23: Gifts | C23: =IFERROR(SUMIF(Transactions!E:E,B23,Transactions!G:G),0) -> 495 | D23: =IFERROR(xlookup(B23,Categories!$A$2:$A$20,Categories!$B$2:$B$20,0),0) -> 0 | E23: =IFERROR(D23-C23,0) -> -495 | F23: =IFERROR(C23/D23,0) -> 0 | G23: =IFERROR(IF(D23=0,"N/A",IF(C23>D23,"🔴 Over Budget",IF(C23/D23>0.8,"🟡 Near Limit","✅ On Track"))),"N/A") -> N/A
B24: Sport & Hobbies | C24: =IFERROR(SUMIF(Transactions!E:E,B24,Transactions!G:G),0) -> 275 | D24: =IFERROR(xlookup(B24,Categories!$A$2:$A$20,Categories!$B$2:$B$20,0),0) -> 0 | E24: =IFERROR(D24-C24,0) -> -275 | F24: =IFERROR(C24/D24,0) -> 0 | G24: =IFERROR(IF(D24=0,"N/A",IF(C24>D24,"🔴 Over Budget",IF(C24/D24>0.8,"🟡 Near Limit","✅ On Track"))),"N/A") -> N/A
B25: Telephone | C25: =IFERROR(SUMIF(Transactions!E:E,B25,Transactions!G:G),0) -> 65 | D25: =IFERROR(xlookup(B25,Categories!$A$2:$A$20,Categories!$B$2:$B$20,0),0) -> 0 | E25: =IFERROR(D25-C25,0) -> -65 | F25: =IFERROR(C25/D25,0) -> 0 | G25: =IFERROR(IF(D25=0,"N/A",IF(C25>D25,"🔴 Over Budget",IF(C25/D25>0.8,"🟡 Near Limit","✅ On Track"))),"N/A") -> N/A
B26: Personal Care | C26: =IFERROR(SUMIF(Transactions!E:E,B26,Transactions!G:G),0) -> 29.99 | D26: =IFERROR(xlookup(B26,Categories!$A$2:$A$20,Categories!$B$2:$B$20,0),0) -> 0 | E26: =IFERROR(D26-C26,0) -> -29.99 | F26: =IFERROR(C26/D26,0) -> 0 | G26: =IFERROR(IF(D26=0,"N/A",IF(C26>D26,"🔴 Over Budget",IF(C26/D26>0.8,"🟡 Near Limit","✅ On Track"))),"N/A") -> N/A
... B30: Transfer | C30: =IFERROR(SUMIF(Transactions!E:E,B30,Transactions!G:G),0) -> 0 | D30: =IFERROR(xlookup(B30,Categories!$A$2:$A$20,Categories!$B$2:$B$20,0),0) -> 0 | E30: =IFERROR(D30-C30,0) -> 0 | F30: =IFERROR(C30/D30,0) -> 0 | G30: =IFERROR(IF(D30=0,"N/A",IF(C30>D30,"🔴 Over Budget",IF(C30/D30>0.8,"🟡 Near Limit","✅ On Track"))),"N/A") -> N/A
B32: QUICK STATS
B33: Total Transactions | D33: Total Fees Paid | F33: Largest Spend | H33: Avg Daily Spend
B34: =COUNTA(Transactions!B2:B200) -> 73 | D34: =IFERROR(SUM(Transactions!F2:F200),0) -> 191.28 | F34: =IFERROR(MAX(Transactions!G2:G200),0) -> 1000 | H34: =IFERROR(SUMIF(Transactions!G2:G200,">"&0,Transactions!G2:G200)/COUNTA(Transactions!B2:B200),0) -> 74.402466
B36: 💡 All formulas are live — add transactions to the Transactions sheet and everything updates automatically. Blue = your inputs.

Sheet Transactions
A1: Date | B1: Description | C1: Type | D1: Money In (R) | E1: Category | F1: Fee (R) | G1: Money Out (R) | H1: Balance (R) | I1: Budget Limit (R) | J1: Status
A2: 46113 | B2: Checkers Sb083793 (Card 9654) | C2: Card | D2: 0 | E2: Groceries | F2: 0 | G2: 66 | H2: 1989.25 | I2: =IFERROR(VLOOKUP(E2,Categories!$A:$B,2,FALSE()),0) -> 800 | J2: =IFERROR(IF(I2=0,"N/A",IF(G2>I2,"🔴 Over Budget","✅ Under Budget")),"N/A") -> ✅ Under Budget
A3: 46113 | B3: Cracker Zacs - Gaap/S Johannesburg | C3: Card | D3: 0 | E3: Sport & Hobbies | F3: 0 | G3: 275 | H3: 1714.25 | I3: =IFERROR(VLOOKUP(E3,Categories!$A:$B,2,FALSE()),0) -> 400 | J3: =IFERROR(IF(I3=0,"N/A",IF(G3>I3,"🔴 Over Budget","✅ Under Budget")),"N/A") -> ✅ Under Budget
A4: 46113 | B4: Lush South Africa Johannesburg | C4: Card | D4: 0 | E4: Gifts | F4: 0 | G4: 495 | H4: 1219.25 | I4: =IFERROR(VLOOKUP(E4,Categories!$A:$B,2,FALSE()),0) -> 500 | J4: =IFERROR(IF(I4=0,"N/A",IF(G4>I4,"🔴 Over Budget","✅ Under Budget")),"N/A") -> ✅ Under Budget
A5: 46113 | B5: Simply Asia Rosebank | C5: Card | D5: 0 | E5: Takeaways | F5: 0 | G5: 280 | H5: 939.25 | I5: =IFERROR(VLOOKUP(E5,Categories!$A:$B,2,FALSE()),0) -> 1500 | J5: =IFERROR(IF(I5=0,"N/A",IF(G5>I5,"🔴 Over Budget","✅ Under Budget")),"N/A") -> ✅ Under Budget
A6: 46113 | B6: Clicks Johannesburg | C6: Card | D6: 0 | E6: Personal Care | F6: 0 | G6: 29.99 | H6: 909.26 | I6: =IFERROR(VLOOKUP(E6,Categories!$A:$B,2,FALSE()),0) -> 200 | J6: =IFERROR(IF(I6=0,"N/A",IF(G6>I6,"🔴 Over Budget","✅ Under Budget")),"N/A") -> ✅ Under Budget
A7: 46113 | B7: Live Better Round-up Transfer | C7: Transfer | D7: 0 | E7: Transfer | F7: 8.02 | G7: 0 | H7: 901.24 | I7: =IFERROR(VLOOKUP(E7,Categories!$A:$B,2,FALSE()),0) -> 500 | J7: =IFERROR(IF(I7=0,"N/A",IF(G7>I7,"🔴 Over Budget","✅ Under Budget")),"N/A") -> ✅ Under Budget
A8: 46113 | B8: Payment Received: M Ahmed | C8: Income | D8: 40 | E8: Other Income | F8: 0 | G8: 0 | H8: 941.24 | I8: =IFERROR(VLOOKUP(E8,Categories!$A:$B,2,FALSE()),0) -> 0 | J8: =IFERROR(IF(I8=0,"N/A",IF(G8>I8,"🔴 Over Budget","✅ Under Budget")),"N/A") -> N/A
A9: 46114 | B9: Shell Benoni (Card 9654) | C9: Card | D9: 0 | E9: Fuel | F9: 0 | G9: 20.5 | H9: 920.74 | I9: =IFERROR(VLOOKUP(E9,Categories!$A:$B,2,FALSE()),0) -> 300 | J9: =IFERROR(IF(I9=0,"N/A",IF(G9>I9,"🔴 Over Budget","✅ Under Budget")),"N/A") -> ✅ Under Budget
A10: 46114 | B10: Recurring Card Purchase: Uber Parktown | C10: Card | D10: 0 | E10: Public Transport | F10: 0 | G10: 38 | H10: 882.74 | I10: =IFERROR(VLOOKUP(E10,Categories!$A:$B,2,FALSE()),0) -> 600 | J10: =IFERROR(IF(I10=0,"N/A",IF(G10>I10,"🔴 Over Budget","✅ Under Budget")),"N/A") -> ✅ Under Budget
A11: 46114 | B11: Live Better Round-up Transfer | C11: Transfer | D11: 0 | E11: Transfer | F11: 14.01 | G11: 0 | H11: 868.73 | I11: =IFERROR(VLOOKUP(E11,Categories!$A:$B,2,FALSE()),0) -> 500 | J11: =IFERROR(IF(I11=0,"N/A",IF(G11>I11,"🔴 Over Budget","✅ Under Budget")),"N/A") -> ✅ Under Budget
A12: 46115 | B12: Live Better Round-up Transfer | C12: Transfer | D12: 0 | E12: Transfer | F12: 11.5 | G12: 0 | H12: 857.23 | I12: =IFERROR(VLOOKUP(E12,Categories!$A:$B,2,FALSE()),0) -> 500 | J12: =IFERROR(IF(I12=0,"N/A",IF(G12>I12,"🔴 Over Budget","✅ Under Budget")),"N/A") -> ✅ Under Budget
A13: 46115 | B13: Dubai Cafe Boksburg | C13: Card | D13: 0 | E13: Digital Payments | F13: 0 | G13: 35 | H13: 822.23 | I13: =IFERROR(VLOOKUP(E13,Categories!$A:$B,2,FALSE()),0) -> 300 | J13: =IFERROR(IF(I13=0,"N/A",IF(G13>I13,"🔴 Over Budget","✅ Under Budget")),"N/A") -> ✅ Under Budget
... A74: 46155 | B74: Live Better Round-up Transfer | C74: Transfer | D74: 0 | E74: Transfer | F74: 5.3 | G74: 0 | H74: 1932.72 | I74: =IFERROR(VLOOKUP(E74,Categories!$A:$B,2,FALSE()),0) -> 500 | J74: =IFERROR(IF(I74=0,"N/A",IF(G74>I74,"🔴 Over Budget","✅ Under Budget")),"N/A") -> ✅ Under Budget

Sheet Lookup
A1: Category | B1: Limit
A2: Takeaways | B2: 1500
A3: Groceries | B3: 800
A4: Public Transport | B4: 600
A5: Cellphone | B5: 800
A6: Movies | B6: 400
A7: Restaurants | B7: 500
A8: Online Store | B8: 400
A9: Digital Payments | B9: 300
A10: Gifts | B10: 500
A11: Sport & Hobbies | B11: 400
A12: Telephone | B12: 200
A13: Personal Care | B13: 200
... A20: Interest | B20: 0

Sheet Savings
A1: SAVINGS TRACKER
A2: Goal | B2: Target (R) | C2: Current (R) | D2: Remaining (R) | E2: Progress %
A3: Laptop | B3: 15000 | C3: 4000 | D3: =B3-C3 -> 11000 | E3: =IFERROR(C3/B3,0) -> 0.26666667
A4: Vacation | B4: 8000 | C4: 2000 | D4: =B4-C4 -> 6000 | E4: =IFERROR(C4/B4,0) -> 0.25
A5: Emergency Fund | B5: 10000 | C5: 3500 | D5: =B5-C5 -> 6500 | E5: =IFERROR(C5/B5,0) -> 0.35
A6: New Phone | B6: 5000 | C6: 1200 | D6: =B6-C6 -> 3800 | E6: =IFERROR(C6/B6,0) -> 0.24
A7: Books/Study | B7: 3000 | C7: 900 | D7: =B7-C7 -> 2100 | E7: =IFERROR(C7/B7,0) -> 0.3

Sheet Categories
A1: Category | B1: Monthly Limit (R) | C1: Actual Spend (R)
A2: Takeaways | B2: 1500 | C2: =IFERROR(SUMIF(Transactions!E:E,A2,Transactions!G:G),0) -> 1015.5
A3: Groceries | B3: 800 | C3: =IFERROR(SUMIF(Transactions!E:E,A3,Transactions!G:G),0) -> 113.5
A4: Public Transport | B4: 600 | C4: =IFERROR(SUMIF(Transactions!E:E,A4,Transactions!G:G),0) -> 382
A5: Cellphone | B5: 800 | C5: =IFERROR(SUMIF(Transactions!E:E,A5,Transactions!G:G),0) -> 660
A6: Movies | B6: 400 | C6: =IFERROR(SUMIF(Transactions!E:E,A6,Transactions!G:G),0) -> 299.9
A7: Restaurants | B7: 500 | C7: =IFERROR(SUMIF(Transactions!E:E,A7,Transactions!G:G),0) -> 199
A8: Online Store | B8: 400 | C8: =IFERROR(SUMIF(Transactions!E:E,A8,Transactions!G:G),0) -> 130.99
A9: Digital Payments | B9: 300 | C9: =IFERROR(SUMIF(Transactions!E:E,A9,Transactions!G:G),0) -> 175
A10: Gifts | B10: 500 | C10: =IFERROR(SUMIF(Transactions!E:E,A10,Transactions!G:G),0) -> 495
A11: Sport & Hobbies | B11: 400 | C11: =IFERROR(SUMIF(Transactions!E:E,A11,Transactions!G:G),0) -> 275
A12: Telephone | B12: 200 | C12: =IFERROR(SUMIF(Transactions!E:E,A12,Transactions!G:G),0) -> 65
A13: Personal Care | B13: 200 | C13: =IFERROR(SUMIF(Transactions!E:E,A13,Transactions!G:G),0) -> 29.99
... A20: Interest | B20: 0 | C20: =IFERROR(SUMIF(Transactions!E:E,A20,Transactions!G:G),0) -> 0
